setup.py
mimicbot_chat/__init__.py
mimicbot_chat/utils.py
mimicbot_chat.egg-info/PKG-INFO
mimicbot_chat.egg-info/SOURCES.txt
mimicbot_chat.egg-info/dependency_links.txt
mimicbot_chat.egg-info/requires.txt
mimicbot_chat.egg-info/top_level.txt