Metadata-Version: 2.1
Name: mimicbot-chat
Version: 1.0.0
Summary: Chat utils for mimicbot
Home-page: https://github.com/CakeCrusher/mimicbot/tree/master/mimicbot/mimicbot_chat
Author: Sebastian Sosa
Author-email: 1sebastian1sosa1@gmail.com
License: MIT License
Platform: UNKNOWN
Classifier: Development Status :: 3 - Alpha
Classifier: Intended Audience :: Science/Research
Classifier: License :: OSI Approved :: MIT License
Classifier: Programming Language :: Python :: 3.10
